{
    "products":[
        {
            "name":"fromHandsToHearts",
            "productCode":"WI_01",
            "displayName": "From Hands to Hearts",
            "description": "There is a famous lullaby “lavender blue dilly dilly, lavender green. When you are king dilly dilly, I shall be queen”. Be the king and queen of your own wild. This card is made with texture card stock and all the Lil elements added are paper cuts. Be the first to order. 😉",
            "imageLogo": "WeddingInvitation_FromHandsToHearts.jpg",
            "overViewImages":[
                "WeddingInvitation_FromHandsToHearts.jpg",
                "WeddingInvitation_GetWellSoon.jpg",
                "WeddingInvitation_SuitorRelish.jpg",
                "WeddingInvitation_TheCoffeeTale.jpg"
            ],
            "cost":{
                "price": "200.00",
                "currency": "INR",
                "code":"INR"
            },
            "categoryCode": "WI"
        },
        {
            "name":"getWellSoon",
            "productCode":"WI_02",
            "displayName": "Get Well Soon Card",
            "description": "There is a famous lullaby “lavender blue dilly dilly, lavender green. When you are king dilly dilly, I shall be queen”. Be the king and queen of your own wild. This card is made with texture card stock and all the Lil elements added are paper cuts. Be the first to order. 😉",
            "imageLogo": "WeddingInvitation_GetWellSoon.jpg",
            "overViewImages":[
                "WeddingInvitation_FromHandsToHearts.jpg",
                "WeddingInvitation_GetWellSoon.jpg",
                "WeddingInvitation_SuitorRelish.jpg",
                "WeddingInvitation_TheCoffeeTale.jpg"
            ],
            "cost":{
                "price": "200.00",
                "currency": "INR",
                "code":"INR"
            },
            "categoryCode": "WI"
        },
        {
            "name":"suitorRelish",
            "productCode":"WI_03",
            "displayName": "Suitor Relish",
            "description": "There is a famous lullaby “lavender blue dilly dilly, lavender green. When you are king dilly dilly, I shall be queen”. Be the king and queen of your own wild. This card is made with texture card stock and all the Lil elements added are paper cuts. Be the first to order. 😉",
            "imageLogo": "WeddingInvitation_SuitorRelish.jpg",
            "overViewImages":[
                "WeddingInvitation_FromHandsToHearts.jpg",
                "WeddingInvitation_GetWellSoon.jpg",
                "WeddingInvitation_SuitorRelish.jpg",
                "WeddingInvitation_TheCoffeeTale.jpg"
            ],
            "cost":{
                "price": "300.00",
                "currency": "USD",
                "code":"$"
            },
            "categoryCode": "WI"
        },
        {
            "name":"theCoffeeTale",
            "productCode":"WI_04",
            "displayName": "The Coffee Tale",
            "description": "There is a famous lullaby “lavender blue dilly dilly, lavender green. When you are king dilly dilly, I shall be queen”. Be the king and queen of your own wild. This card is made with texture card stock and all the Lil elements added are paper cuts. Be the first to order. 😉",
            "imageLogo": "WeddingInvitation_TheCoffeeTale.jpg",
            "overViewImages":[
                "WeddingInvitation_FromHandsToHearts.jpg",
                "WeddingInvitation_GetWellSoon.jpg",
                "WeddingInvitation_SuitorRelish.jpg",
                "WeddingInvitation_TheCoffeeTale.jpg"
            ],
            "cost":{
                "price": "100.00",
                "currency": "INR",
                "code":"INR"
            },
            "categoryCode": "WI"
        },
        {
            "name":"thePurpleGrandeur",
            "productCode":"WI_05",
            "displayName": "The Purple Grandeur",
            "description": "There is a famous lullaby “lavender blue dilly dilly, lavender green. When you are king dilly dilly, I shall be queen”. Be the king and queen of your own wild. This card is made with texture card stock and all the Lil elements added are paper cuts. Be the first to order. 😉",
            "imageLogo": "WeddingInvitation_ThePurpleGrandeur.jpg",
            "overViewImages":[
                "WeddingInvitation_FromHandsToHearts.jpg",
                "WeddingInvitation_GetWellSoon.jpg",
                "WeddingInvitation_SuitorRelish.jpg",
                "WeddingInvitation_TheCoffeeTale.jpg"
            ],
            "cost":{
                "price": "500.00",
                "currency": "INR",
                "code":"INR"
            },
            "categoryCode": "WI"
        },
        {
            "name":"wildLove",
            "productCode":"WI_06",
            "displayName": "Wild Love",
            "description": "There is a famous lullaby “lavender blue dilly dilly, lavender green. When you are king dilly dilly, I shall be queen”. Be the king and queen of your own wild. This card is made with texture card stock and all the Lil elements added are paper cuts. Be the first to order. 😉",
            "imageLogo": "WeddingInvitation_WildLove.jpg",
            "cost":{
                "price": "200.00",
                "currency": "INR",
                "code":"INR"
            },
            "categoryCode": "WI"
        },
        {
            "name":"woodenCoaster",
            "productCode":"WI_07",
            "displayName": "Wooden Coaster",
            "description": "There is a famous lullaby “lavender blue dilly dilly, lavender green. When you are king dilly dilly, I shall be queen”. Be the king and queen of your own wild. This card is made with texture card stock and all the Lil elements added are paper cuts. Be the first to order. 😉",
            "imageLogo": "WeddingInvitation_WoodenCoaster.jpg",
            "cost":{
                "price": "200.00",
                "currency": "INR",
                "code":"INR"
            },
            "categoryCode": "WI"
        },
        {
            "name":"youMeAndCoffee",
            "productCode":"WI_08",
            "displayName": "You Me and Coffee",
            "description": "There is a famous lullaby “lavender blue dilly dilly, lavender green. When you are king dilly dilly, I shall be queen”. Be the king and queen of your own wild. This card is made with texture card stock and all the Lil elements added are paper cuts. Be the first to order. 😉",
            "imageLogo": "WeddingInvitation_YouMeAndCoffee.jpg",
            "cost":{
                "price": "200.00",
                "currency": "INR",
                "code":"INR"
            },
            "categoryCode": "WI"
        },
        {
            "name":"elephant",
            "productCode":"G_01",
            "displayName": "Elephant with baby",
            "description": "There is a famous lullaby “lavender blue dilly dilly, lavender green. When you are king dilly dilly, I shall be queen”. Be the king and queen of your own wild. This card is made with texture card stock and all the Lil elements added are paper cuts. Be the first to order. 😉",
            "imageLogo": "Gifts_Elephant.jpg",
            "cost":{
                "price": "200.00",
                "currency": "INR",
                "code":"INR"
            },
            "categoryCode": "Gifts"
        },
        {
            "name":"slowAndSteady",
            "productCode":"G_02",
            "displayName": "Slow and Steady",
            "description": "There is a famous lullaby “lavender blue dilly dilly, lavender green. When you are king dilly dilly, I shall be queen”. Be the king and queen of your own wild. This card is made with texture card stock and all the Lil elements added are paper cuts. Be the first to order. 😉",
            "imageLogo": "Gifts_SlowAndSteady.jpg",
            "cost":{
                "price": "200.00",
                "currency": "INR",
                "code":"INR"
            },
            "categoryCode": "Gifts"
        },
        {
            "name":"theWoman",
            "productCode":"G_03",
            "displayName": "The Woman",
            "description": "There is a famous lullaby “lavender blue dilly dilly, lavender green. When you are king dilly dilly, I shall be queen”. Be the king and queen of your own wild. This card is made with texture card stock and all the Lil elements added are paper cuts. Be the first to order. 😉",
            "imageLogo": "Gifts_TheWoman.jpg",
            "cost":{
                "price": "200.00",
                "currency": "INR",
                "code":"INR"
            },
            "categoryCode": "Gifts"
        },
        {
            "name":"swan",
            "productCode":"B_01",
            "displayName": "Swan",
            "description": "There is a famous lullaby “lavender blue dilly dilly, lavender green. When you are king dilly dilly, I shall be queen”. Be the king and queen of your own wild. This card is made with texture card stock and all the Lil elements added are paper cuts. Be the first to order. 😉",
            "imageLogo": "Backdrops_Swan.jpg",
            "cost":{
                "price": "200.00",
                "currency": "INR",
                "code":"INR"
            },
            "categoryCode": "Backdrops"
        }
    ]
}